sc_config/__init__.py
sc_config/config.py
sc_config/config_manager.py
sc_config/config_utils.py
sc_config/utils.py
sc_config/validator.py
sc_config/handlers/__init__.py
sc_config/handlers/argparse.py
sc_config/handlers/base.py
sc_config/handlers/environment.py
sc_config/handlers/etcd.py
sc_config/handlers/file.py
sc_config/handlers/memory.py
sc_config/handlers/raw.py
sc_config/handlers/files/__init__.py
sc_config/handlers/files/base.py
sc_config/handlers/files/ini.py
sc_config/handlers/files/json.py
sc_config/handlers/files/yaml.py
sc_config-0.0.15.dist-info/licenses/LICENSE
tests/__init__.py
tests/test_config.py
tests/sample_config/__init__.py
tests/sample_config/default.py
sc_config-0.0.15.dist-info/METADATA
sc_config-0.0.15.dist-info/WHEEL
sc_config-0.0.15.dist-info/top_level.txt
sc_config-0.0.15.dist-info/RECORD
