Metadata-Version: 2.4
Name: sc-config
Version: 0.0.15
Summary: A simple Python configuration file operator
Home-page: https://github.com/Scott-Lau/sc-config
Author: Scott Lau
Author-email: exceedego@126.com
License: MIT
Keywords: python config
Platform: POSIX
Classifier: Programming Language :: Python :: 3
Classifier: Programming Language :: Python :: 3.6
Classifier: Programming Language :: Python :: 3.7
Classifier: Programming Language :: Python :: 3.8
Classifier: Programming Language :: Python :: 3.9
Classifier: License :: OSI Approved :: MIT License
Classifier: Operating System :: OS Independent
Classifier: Topic :: Software Development
Classifier: Topic :: Utilities
Requires-Python: >=3.6
License-File: LICENSE
Requires-Dist: ruamel.yaml>=0.17.17
Requires-Dist: Jinja2>=2.0
Requires-Dist: Cerberus>=1.3.1
Requires-Dist: MarkupSafe>=2.0.1
Dynamic: author
Dynamic: author-email
Dynamic: classifier
Dynamic: description
Dynamic: home-page
Dynamic: keywords
Dynamic: license
Dynamic: license-file
Dynamic: platform
Dynamic: requires-dist
Dynamic: requires-python
Dynamic: summary
